qwl_crapstar/__init__.py
qwl_crapstar/core/__init__.py
qwl_crapstar/core/config.py
qwl_crapstar/core/llm_providers.py
qwl_crapstar/core/orchestrator.py
qwl_crapstar/core/processors.py
qwl_crapstar/core/schema.py
qwl_crapstar/core/scraper.py
qwl_crapstar/defenses/__init__.py
qwl_crapstar/execution/__init__.py
qwl_crapstar/execution/browser_engine.py
qwl_crapstar/exporters/__init__.py
qwl_crapstar/extractors/__init__.py
qwl_crapstar/schemas/__init__.py
qwl_crapstar/utils/__init__.py
qwlcrapstar-0.1.11.dist-info/licenses/LICENSE
qwlcrapstar-0.1.11.dist-info/METADATA
qwlcrapstar-0.1.11.dist-info/WHEEL
qwlcrapstar-0.1.11.dist-info/top_level.txt
qwlcrapstar-0.1.11.dist-info/RECORD
