Metadata-Version: 2.4
Name: qwlcrapstar
Version: 0.1.11
Summary: Universal AI-Powered Web Scraper Library
Author-email: QwlCrapstar Team <research@qwlcrapstar.ai>
License: MIT
Project-URL: Homepage, https://github.com/Ranzim/QwlCrapStar
Project-URL: Repository, https://github.com/Ranzim/QwlCrapStar.git
Project-URL: Issues, https://github.com/Ranzim/QwlCrapStar/issues
Project-URL: Documentation, https://github.com/Ranzim/QwlCrapStar/blob/main/README.md
Keywords: scraper,ai,llm,automation,agent,web-scraping,playwright
Classifier: Development Status :: 4 - Beta
Classifier: Intended Audience :: Developers
Classifier: License :: OSI Approved :: MIT License
Classifier: Programming Language :: Python :: 3.9
Classifier: Programming Language :: Python :: 3.10
Classifier: Programming Language :: Python :: 3.11
Classifier: Topic :: Software Development :: Libraries :: Python Modules
Classifier: Topic :: Internet :: WWW/HTTP
Requires-Python: >=3.9
License-File: LICENSE
Requires-Dist: langchain>=0.1.0
Requires-Dist: langchain-community
Requires-Dist: langchain-openai
Requires-Dist: langchain-anthropic
Requires-Dist: langchain-groq
Requires-Dist: playwright>=1.40.0
Requires-Dist: pydantic>=2.0.0
Requires-Dist: python-dotenv>=1.0.0
Requires-Dist: pandas>=2.0.0
Requires-Dist: beautifulsoup4>=4.12.0
Requires-Dist: requests>=2.31.0
Requires-Dist: pyyaml>=6.0.0
Provides-Extra: dev
Requires-Dist: pytest>=7.0.0; extra == "dev"
Requires-Dist: pytest-asyncio; extra == "dev"
Requires-Dist: pytest-cov; extra == "dev"
Requires-Dist: black; extra == "dev"
Requires-Dist: isort; extra == "dev"
Requires-Dist: mypy; extra == "dev"
Provides-Extra: db
Requires-Dist: pymongo; extra == "db"
Requires-Dist: psycopg2-binary; extra == "db"
Dynamic: license-file
